MANIFEST.in
requirements.txt
setup.py
aloft/__init__.py
aloft/__main__.py
aloft.py.egg-info/PKG-INFO
aloft.py.egg-info/SOURCES.txt
aloft.py.egg-info/dependency_links.txt
aloft.py.egg-info/requires.txt
aloft.py.egg-info/top_level.txt