Metadata-Version: 1.1
Name: aloft.py
Version: 0.0.4
Summary: A simple API for getting winds aloft data from NOAA
Home-page: https://github.com/natemara/aloft.py
Author: Nate Mara
Author-email: natemara@gmail.com
License: MIT
Keywords: aviation weather winds aloft
Platform: UNKNOWN
Classifier: Development Status :: 3 - Alpha
Classifier: Topic :: Utilities
Classifier: License :: OSI Approved :: MIT License
